LICENSE.txt
README.md
setup.py
ilap/__init__.py
ilap/ilap_utils.py
ilap.egg-info/PKG-INFO
ilap.egg-info/SOURCES.txt
ilap.egg-info/dependency_links.txt
ilap.egg-info/requires.txt
ilap.egg-info/top_level.txt
ilap.egg-info/zip-safe