Metadata-Version: 2.1
Name: ilap
Version: 0.1
Summary: Numerical Laplace transform inversion tools
Home-page: https://gitlab.com/scottkalevhansen/ilap
Author: Scott K. Hansen
Author-email: skh@bgu.ac.il
License: UNKNOWN
Platform: UNKNOWN
